dp_streamlit_antd/__init__.py
dp_streamlit_antd/breadcrumb/__init__.py
dp_streamlit_antd/cards/__init__.py
dp_streamlit_antd/cascader/__init__.py
dp_streamlit_antd/pager/__init__.py
dp_streamlit_antd/result/__init__.py
dp_streamlit_antd/steps/__init__.py
dp_streamlit_antd/table/__init__.py
dp_streamlit_antd/tabs/__init__.py
dp_streamlit_antd/tag/__init__.py
streamlit_antd/__init__.py
streamlit_antd/breadcrumb/__init__.py
streamlit_antd/cards/__init__.py
streamlit_antd/cascader/__init__.py
streamlit_antd/pager/__init__.py
streamlit_antd/result/__init__.py
streamlit_antd/steps/__init__.py
streamlit_antd/table/__init__.py
streamlit_antd/tabs/__init__.py
streamlit_antd/tag/__init__.py
dp_streamlit_antd-0.8.5.dist-info/LICENSE
dp_streamlit_antd-0.8.5.dist-info/METADATA
dp_streamlit_antd-0.8.5.dist-info/WHEEL
dp_streamlit_antd-0.8.5.dist-info/top_level.txt
dp_streamlit_antd-0.8.5.dist-info/RECORD
