Metadata-Version: 2.1
Name: dp-streamlit-antd
Version: 0.8.5
Summary: UNKNOWN
Home-page: https://github.com/pragmatic-streamlit/streamlit-antd
Author: mapix
Author-email: mapix.me@gmail.com
License: UNKNOWN
Platform: UNKNOWN
Requires-Python: >=3.6
Requires-Dist: streamlit (>=0.63)
